README.md
setup.py
jupytergitcommit/__init__.py
jupytergitcommit/handlers.py
jupytergitcommit.egg-info/PKG-INFO
jupytergitcommit.egg-info/SOURCES.txt
jupytergitcommit.egg-info/dependency_links.txt
jupytergitcommit.egg-info/requires.txt
jupytergitcommit.egg-info/top_level.txt