Metadata-Version: 1.0
Name: jupytergitcommit
Version: 1.0
Summary: Jupyter extension to enable user push notebooks to a git repo
Home-page: https://github.com/newellp2019/jupytergitcommit
Author: Peter Newell
Author-email: UNKNOWN
License: UNKNOWN
Platform: UNKNOWN
